prefect_bitbucket/__init__.py
prefect_bitbucket/_version.py
prefect_bitbucket/credentials.py
prefect_bitbucket/repository.py
prefect_bitbucket-0.3.4.dist-info/licenses/LICENSE
prefect_bitbucket-0.3.4.dist-info/METADATA
prefect_bitbucket-0.3.4.dist-info/WHEEL
prefect_bitbucket-0.3.4.dist-info/entry_points.txt
prefect_bitbucket-0.3.4.dist-info/top_level.txt
prefect_bitbucket-0.3.4.dist-info/RECORD
