Metadata-Version: 2.4
Name: prefect-bitbucket
Version: 0.3.4
Summary: Prefect integrations for working with Bitbucket repositories.
Author-email: "Prefect Technologies, Inc." <help@prefect.io>
License: Apache License 2.0
Project-URL: Homepage, https://github.com/PrefectHQ/prefect/tree/main/src/integrations/prefect-bitbucket
Keywords: prefect
Classifier: Natural Language :: English
Classifier: Intended Audience :: Developers
Classifier: Intended Audience :: System Administrators
Classifier: License :: OSI Approved :: Apache Software License
Classifier: Programming Language :: Python :: 3 :: Only
Classifier: Programming Language :: Python :: 3.10
Classifier: Programming Language :: Python :: 3.11
Classifier: Programming Language :: Python :: 3.12
Classifier: Programming Language :: Python :: 3.13
Classifier: Topic :: Software Development :: Libraries
Requires-Python: >=3.10
License-File: LICENSE
Requires-Dist: prefect>=3.0.0
Requires-Dist: pydantic>=2.4
Requires-Dist: atlassian-python-api!=3.41.5,!=3.41.6,!=3.41.7,!=3.41.8,>=3.32.1
Dynamic: license-file
